[
  {
    "id": "loeco_ttn",
    "display_name": "LoRa TTN Node",
    "owner": "MeteoALabs",
    "sensor_type": "ttn-node",
    "latitude": 52.1234,
    "longitude": 5.1334,
    "temperature": 10.27,
    "metrics": {
      "temperature_c": 10.27,
      "humidity_pct": 75.6,
      "battery_voltage_v": 2.99,
      "dew_point_c": 6.15,
      "wbgt_c": 9.32
    },
    "last_update": "2026-03-04 10:38 UTC"
  },
  {
    "id": "ecowitt_home",
    "display_name": "EcoWitt WS2910",
    "owner": "MeteoALabs",
    "sensor_type": "ecowitt-wh65",
    "latitude": 52.1234,
    "longitude": 5.1234,
    "temperature": 10.7,
    "metrics": {
      "temperature_c": 10.7,
      "humidity_pct": 75.0,
      "pressure_hpa": 1026.2,
      "dew_point_c": 6.5,
      "feels_like_c": 10.7,
      "wind_speed_ms": 3.4,
      "wind_gust_ms": 5.4,
      "wind_dir_deg": 69.0,
      "solar_wm2": 299.8,
      "rain_daily_mm": 0.0,
      "rain_rate_mmhr": 0.0,
      "wbgt_c": 11.36,
      "globe_temp_c": 18.34
    },
    "last_update": "2026-03-04 10:38 UTC"
  },
  {
    "id": "Eelde_Airport",
    "display_name": "Eelde_Airport",
    "owner": "MeteoALabs",
    "sensor_type": "ecowitt-Temponly",
    "latitude": 53.1284,
    "longitude": 6.5848,
    "temperature": 10.6,
    "metrics": {
      "temperature_c": 10.6,
      "humidity_pct": 74.0,
      "pressure_hpa": 1028.4
    },
    "last_update": "2026-03-04 10:38 UTC"
  },
  {
    "id": "AMS_VU_Roof_Top",
    "display_name": "AMS_VU_Roof_Top",
    "owner": "VU",
    "sensor_type": "ecowitt-Wittboy",
    "latitude": 52.3343,
    "longitude": 4.86683,
    "temperature": 9.9,
    "metrics": {
      "temperature_c": 9.9,
      "humidity_pct": 71.0,
      "pressure_hpa": 1020.7,
      "dew_point_c": 4.9,
      "feels_like_c": 8.7,
      "wind_speed_ms": 9.0,
      "wind_gust_ms": 13.0,
      "wind_dir_deg": 157.0,
      "solar_wm2": 280.0,
      "rain_daily_mm": 0.0,
      "rain_rate_mmhr": 0.0,
      "wbgt_c": 7.89,
      "globe_temp_c": 14.1
    },
    "last_update": "2026-03-04 10:38 UTC"
  },
  {
    "id": "BON006_Kralendijk_Haven",
    "display_name": "BON006_Kralendijk_Haven",
    "owner": "BES AioWS Network",
    "sensor_type": "ecowitt-ws2910",
    "latitude": 12.148319,
    "longitude": -68.276546,
    "temperature": 26.6,
    "metrics": {
      "temperature_c": 26.6,
      "humidity_pct": 71.0,
      "pressure_hpa": 1011.1,
      "dew_point_c": 20.9,
      "feels_like_c": 26.6,
      "wind_speed_ms": 28.3,
      "wind_gust_ms": 38.5,
      "wind_dir_deg": 117.0,
      "solar_wm2": 0.3,
      "rain_daily_mm": 0.0,
      "rain_rate_mmhr": 0.0,
      "wbgt_c": 17.56,
      "globe_temp_c": 28.16
    },
    "last_update": "2026-03-04 10:38 UTC"
  },
  {
    "id": "BON003_Rincon",
    "display_name": "BON003_Rincon",
    "owner": "BES AioWS Network",
    "sensor_type": "ecowitt-ws2910",
    "latitude": 12.233157,
    "longitude": -68.331587,
    "temperature": 26.1,
    "metrics": {
      "temperature_c": 26.1,
      "humidity_pct": 77.0,
      "pressure_hpa": 1012.0,
      "dew_point_c": 21.7,
      "feels_like_c": 26.1,
      "wind_speed_ms": 6.1,
      "wind_gust_ms": 18.4,
      "wind_dir_deg": 99.0,
      "solar_wm2": 0.1,
      "rain_daily_mm": 0.0,
      "rain_rate_mmhr": 0.0,
      "wbgt_c": 25.01,
      "globe_temp_c": 29.89
    },
    "last_update": "2026-03-04 10:38 UTC"
  },
  {
    "id": "BON002_Washington_Slagbaai",
    "display_name": "BON002_Washington_Slagbaai",
    "owner": "BES AioWS Network",
    "sensor_type": "ecowitt-ws2910",
    "latitude": 12.269665,
    "longitude": -68.345604,
    "temperature": 24.8,
    "metrics": {
      "temperature_c": 24.8,
      "humidity_pct": 85.0,
      "pressure_hpa": 1011.3,
      "dew_point_c": 22.2,
      "feels_like_c": 24.8,
      "wind_speed_ms": 15.5,
      "wind_gust_ms": 22.0,
      "wind_dir_deg": 102.0,
      "solar_wm2": 0.1,
      "rain_daily_mm": 3.0,
      "rain_rate_mmhr": 0.0,
      "wbgt_c": 21.69,
      "globe_temp_c": 26.98
    },
    "last_update": "2026-03-04 10:38 UTC"
  },
  {
    "id": "BON004_Bonaire_Galileo",
    "display_name": "BON004_Bonaire_Galileo",
    "owner": "BES AioWS Network",
    "sensor_type": "ecowitt-ws2910",
    "latitude": 12.213874,
    "longitude": -68.323051,
    "temperature": 25.6,
    "metrics": {
      "temperature_c": 25.6,
      "humidity_pct": 78.0,
      "pressure_hpa": 1013.3,
      "dew_point_c": 21.5,
      "feels_like_c": 25.6,
      "wind_speed_ms": 17.4,
      "wind_gust_ms": 27.7,
      "wind_dir_deg": 108.0,
      "solar_wm2": 0.1,
      "rain_daily_mm": 0.0,
      "rain_rate_mmhr": 0.0,
      "wbgt_c": 20.94,
      "globe_temp_c": 27.65
    },
    "last_update": "2026-03-04 10:38 UTC"
  },
  {
    "id": "BON007_Sur",
    "display_name": "BON007_Sur",
    "owner": "BES AioWS Network",
    "sensor_type": "ecowitt-ws2910",
    "latitude": 12.029204,
    "longitude": -68.25307,
    "temperature": null,
    "metrics": {},
    "last_update": "—"
  },
  {
    "id": "BON005_Lagun",
    "display_name": "BON005_Lagun",
    "owner": "BES AioWS Network",
    "sensor_type": "ecowitt-ws2910",
    "latitude": 12.17686,
    "longitude": -68.227141,
    "temperature": 26.9,
    "metrics": {
      "temperature_c": 26.9,
      "humidity_pct": 75.0,
      "pressure_hpa": 1011.7,
      "dew_point_c": 22.0,
      "feels_like_c": 29.0,
      "wind_speed_ms": 23.0,
      "wind_gust_ms": 34.9,
      "wind_dir_deg": 85.0,
      "solar_wm2": 0.1,
      "rain_daily_mm": 0.0,
      "rain_rate_mmhr": 0.0,
      "wbgt_c": 20.01,
      "globe_temp_c": 28.68
    },
    "last_update": "2026-03-04 10:38 UTC"
  },
  {
    "id": "SAB006_The_Harbor",
    "display_name": "SAB006_The_Harbor",
    "owner": "BES AioWS Network",
    "sensor_type": "ecowitt-ws2910",
    "latitude": 17.616269,
    "longitude": -63.250914,
    "temperature": 25.7,
    "metrics": {
      "temperature_c": 25.7,
      "humidity_pct": 75.0,
      "pressure_hpa": 1014.3,
      "dew_point_c": 20.9,
      "feels_like_c": 25.7,
      "wind_speed_ms": 30.7,
      "wind_gust_ms": 46.1,
      "wind_dir_deg": 111.0,
      "solar_wm2": 5.7,
      "rain_daily_mm": 0.0,
      "rain_rate_mmhr": 0.0,
      "wbgt_c": 16.48,
      "globe_temp_c": 27.17
    },
    "last_update": "2026-03-04 10:38 UTC"
  },
  {
    "id": "SAB005_The_Bottom",
    "display_name": "SAB005_The_Bottom",
    "owner": "BES AioWS Network",
    "sensor_type": "ecowitt-ws2910",
    "latitude": 17.62597,
    "longitude": -63.247604,
    "temperature": 23.6,
    "metrics": {
      "temperature_c": 23.6,
      "humidity_pct": 83.0,
      "pressure_hpa": 1013.7,
      "dew_point_c": 20.4,
      "feels_like_c": 23.6,
      "wind_speed_ms": 7.6,
      "wind_gust_ms": 14.8,
      "wind_dir_deg": 185.0,
      "solar_wm2": 2.3,
      "rain_daily_mm": 0.2,
      "rain_rate_mmhr": 0.0,
      "wbgt_c": 22.63,
      "globe_temp_c": 26.8
    },
    "last_update": "2026-03-04 10:38 UTC"
  },
  {
    "id": "SAB004_Julianas_Hotel",
    "display_name": "SAB004_Julianas_Hotel",
    "owner": "BES AioWS Network",
    "sensor_type": "ecowitt-ws2910",
    "latitude": 17.627092,
    "longitude": -63.231801,
    "temperature": null,
    "metrics": {},
    "last_update": "—"
  },
  {
    "id": "SAB001_The_Road",
    "display_name": "SAB001_The_Road",
    "owner": "BES AioWS Network",
    "sensor_type": "ecowitt-ws2910",
    "latitude": 17.643074,
    "longitude": -63.227046,
    "temperature": 23.8,
    "metrics": {
      "temperature_c": 23.8,
      "humidity_pct": 84.0,
      "pressure_hpa": 1012.1,
      "dew_point_c": 20.9,
      "feels_like_c": 23.8,
      "wind_speed_ms": 24.8,
      "wind_gust_ms": 36.7,
      "wind_dir_deg": 118.0,
      "solar_wm2": 7.7,
      "rain_daily_mm": 0.0,
      "rain_rate_mmhr": 0.0,
      "wbgt_c": 17.53,
      "globe_temp_c": 25.42
    },
    "last_update": "2026-03-04 10:38 UTC"
  },
  {
    "id": "SAB002_The_Church",
    "display_name": "SAB002_The_Church",
    "owner": "BES AioWS Network",
    "sensor_type": "ecowitt-ws2910",
    "latitude": 17.638941,
    "longitude": -63.229518,
    "temperature": 21.9,
    "metrics": {
      "temperature_c": 21.9,
      "humidity_pct": 91.0,
      "pressure_hpa": 1012.2,
      "dew_point_c": 20.3,
      "feels_like_c": 21.9,
      "wind_speed_ms": 10.9,
      "wind_gust_ms": 18.4,
      "wind_dir_deg": 153.0,
      "solar_wm2": 7.3,
      "rain_daily_mm": 0.0,
      "rain_rate_mmhr": 0.0,
      "wbgt_c": 20.72,
      "globe_temp_c": 24.44
    },
    "last_update": "2026-03-04 10:38 UTC"
  },
  {
    "id": "SAB003_The_Level",
    "display_name": "SAB003_The_Level",
    "owner": "BES AioWS Network",
    "sensor_type": "ecowitt-ws2910",
    "latitude": 17.628069,
    "longitude": -63.227442,
    "temperature": 20.9,
    "metrics": {
      "temperature_c": 20.9,
      "humidity_pct": 97.0,
      "pressure_hpa": 1012.5,
      "dew_point_c": 20.4,
      "feels_like_c": 20.9,
      "wind_speed_ms": 9.3,
      "wind_gust_ms": 22.0,
      "wind_dir_deg": 64.0,
      "solar_wm2": 7.2,
      "rain_daily_mm": 0.0,
      "rain_rate_mmhr": 0.0,
      "wbgt_c": 20.86,
      "globe_temp_c": 23.65
    },
    "last_update": "2026-03-04 10:38 UTC"
  },
  {
    "id": "EUX001_The_Harbor",
    "display_name": "EUX001_The_Harbor",
    "owner": "BES AioWS Network",
    "sensor_type": "ecowitt-ws2910",
    "latitude": 17.47798,
    "longitude": -62.985968,
    "temperature": 23.8,
    "metrics": {
      "temperature_c": 23.8,
      "humidity_pct": 87.0,
      "pressure_hpa": 1017.2,
      "dew_point_c": 21.5,
      "feels_like_c": 23.8,
      "wind_speed_ms": 8.1,
      "wind_gust_ms": 14.8,
      "wind_dir_deg": 180.0,
      "solar_wm2": 2.5,
      "rain_daily_mm": 7.4,
      "rain_rate_mmhr": 0.0,
      "wbgt_c": 23.25,
      "globe_temp_c": 26.92
    },
    "last_update": "2026-03-04 10:38 UTC"
  },
  {
    "id": "EUX002_Upper_Town",
    "display_name": "EUX002_Upper_Town",
    "owner": "BES AioWS Network",
    "sensor_type": "ecowitt-ws2910",
    "latitude": 17.485321,
    "longitude": -62.983726,
    "temperature": 23.0,
    "metrics": {
      "temperature_c": 23.0,
      "humidity_pct": 93.0,
      "pressure_hpa": 1014.4,
      "dew_point_c": 21.8,
      "feels_like_c": 23.0,
      "wind_speed_ms": 4.3,
      "wind_gust_ms": 5.4,
      "wind_dir_deg": 304.0,
      "solar_wm2": 4.1,
      "rain_daily_mm": 2.8,
      "rain_rate_mmhr": 1.8,
      "wbgt_c": 24.53,
      "globe_temp_c": 27.48
    },
    "last_update": "2026-03-04 10:38 UTC"
  },
  {
    "id": "EUX003_The_Quill_Garden",
    "display_name": "EUX003_The_Quill_Garden",
    "owner": "BES AioWS Network",
    "sensor_type": "ecowitt-ws2910",
    "latitude": 17.487301,
    "longitude": -62.96904,
    "temperature": 22.7,
    "metrics": {
      "temperature_c": 22.7,
      "humidity_pct": 95.0,
      "pressure_hpa": 1011.9,
      "dew_point_c": 21.9,
      "feels_like_c": 22.7,
      "wind_speed_ms": 3.0,
      "wind_gust_ms": 13.0,
      "wind_dir_deg": 80.0,
      "solar_wm2": 4.4,
      "rain_daily_mm": 3.6,
      "rain_rate_mmhr": 1.2,
      "wbgt_c": 25.07,
      "globe_temp_c": 28.2
    },
    "last_update": "2026-03-04 10:38 UTC"
  },
  {
    "id": "EUX004_EOC",
    "display_name": "EUX004_EOC",
    "owner": "BES AioWS Network",
    "sensor_type": "ecowitt-ws2910",
    "latitude": 17.480953,
    "longitude": -62.980393,
    "temperature": 23.0,
    "metrics": {
      "temperature_c": 23.0,
      "humidity_pct": 91.0,
      "pressure_hpa": 1013.6,
      "dew_point_c": 21.4,
      "feels_like_c": 23.0,
      "wind_speed_ms": 15.3,
      "wind_gust_ms": 22.0,
      "wind_dir_deg": 117.0,
      "solar_wm2": 5.2,
      "rain_daily_mm": 4.0,
      "rain_rate_mmhr": 1.2,
      "wbgt_c": 20.49,
      "globe_temp_c": 25.14
    },
    "last_update": "2026-03-04 10:38 UTC"
  },
  {
    "id": "EUX005_Drop_off",
    "display_name": "EUX005_Drop_off",
    "owner": "BES AioWS Network",
    "sensor_type": "ecowitt-ws2910",
    "latitude": 17.465822,
    "longitude": -62.971836,
    "temperature": 23.0,
    "metrics": {
      "temperature_c": 23.0,
      "humidity_pct": 94.0,
      "pressure_hpa": 1012.5,
      "dew_point_c": 22.0,
      "feels_like_c": 23.0,
      "wind_speed_ms": 8.8,
      "wind_gust_ms": 14.8,
      "wind_dir_deg": 103.0,
      "solar_wm2": 2.5,
      "rain_daily_mm": 7.9,
      "rain_rate_mmhr": 0.0,
      "wbgt_c": 23.01,
      "globe_temp_c": 25.96
    },
    "last_update": "2026-03-04 10:39 UTC"
  },
  {
    "id": "KNMI_Saba_Airport",
    "display_name": "KNMI_Saba_Airport",
    "owner": "KNMI",
    "sensor_type": "knmi-aws",
    "latitude": 17.6461,
    "longitude": -63.2208,
    "temperature": 25.4,
    "metrics": {
      "temperature_c": 25.4,
      "humidity_pct": 79.0,
      "pressure_hpa": 1016.01,
      "dew_point_c": 21.7,
      "wind_speed_ms": 8.22,
      "wind_dir_deg": 92.3,
      "solar_wm2": 2.0,
      "wbgt_c": 25.45,
      "globe_temp_c": 30.01
    },
    "last_update": "2026-03-04 10:39 UTC"
  },
  {
    "id": "KNMI_Sint_Eustatius_Airport",
    "display_name": "KNMI_Sint_Eustatius_Airport",
    "owner": "KNMI",
    "sensor_type": "knmi-aws",
    "latitude": 17.4956,
    "longitude": -62.9828,
    "temperature": 23.3,
    "metrics": {
      "temperature_c": 23.3,
      "humidity_pct": 95.0,
      "pressure_hpa": 1016.37,
      "dew_point_c": 22.5,
      "wind_speed_ms": 4.55,
      "wind_dir_deg": 81.3,
      "solar_wm2": 2.0,
      "wbgt_c": 26.13,
      "globe_temp_c": 29.78
    },
    "last_update": "2026-03-04 10:39 UTC"
  },
  {
    "id": "KNMI_Bonaire_Airport",
    "display_name": "KNMI_Bonaire_Airport",
    "owner": "KNMI",
    "sensor_type": "knmi-aws-aerodrome",
    "latitude": 12.13,
    "longitude": -68.2758,
    "temperature": 26.0,
    "metrics": {
      "temperature_c": 26.0,
      "humidity_pct": 73.0,
      "pressure_hpa": 1012.21,
      "dew_point_c": 20.9,
      "wind_speed_ms": 7.61,
      "wind_dir_deg": 94.9,
      "solar_wm2": 0.0,
      "wbgt_c": 23.96,
      "globe_temp_c": 29.34
    },
    "last_update": "2026-03-04 10:39 UTC"
  }
]