{
  "generated_utc": "2026-03-04 18:41 UTC",
  "window_days": 7,
  "record_count": 1940,
  "metrics": {
    "temperature_c": {
      "label": "Temperatuur",
      "unit": "°C",
      "color": "#ff6b6b",
      "accent": "#ff4d8d",
      "latest": 8.3,
      "mean": 9.7,
      "min": 1.5,
      "max": 18.9,
      "std": 3.56,
      "trend": "down",
      "trend_value": -3.9,
      "arrow": "↓"
    },
    "humidity_pct": {
      "label": "Rel.vochtigheid",
      "unit": "%",
      "color": "#4ecdc4",
      "accent": "#2dd4bf",
      "latest": 79.0,
      "mean": 83.91,
      "min": 46.0,
      "max": 99.0,
      "std": 11.03,
      "trend": "up",
      "trend_value": 8.0,
      "arrow": "→"
    },
    "pressure_hpa": {
      "label": "Luchtdruk",
      "unit": "hPa",
      "color": "#45b7d1",
      "accent": "#2ea8e6",
      "latest": 1025.7,
      "mean": 1018.89,
      "min": 1011.5,
      "max": 1029.5,
      "std": 5.2,
      "trend": "down",
      "trend_value": -1.8,
      "arrow": "→"
    }
  },
  "date_range": {
    "start": "2026-02-25 18:45",
    "end": "2026-03-04 18:30"
  }
}